django_esm/__init__.py
django_esm/_version.py
django_esm/apps.py
django_esm/checks.py
django_esm/conf.py
django_esm/forms.py
django_esm/wsgi.py
django_esm/management/__init__.py
django_esm/management/commands/__init__.py
django_esm/management/commands/collectstatic.py
django_esm/management/commands/esm.py
django_esm/templatetags/__init__.py
django_esm/templatetags/esm.py
django_esm-0.8.2.dist-info/licenses/LICENSE
django_esm-0.8.2.dist-info/WHEEL
django_esm-0.8.2.dist-info/METADATA
django_esm-0.8.2.dist-info/RECORD
