Metadata-Version: 2.4
Name: django-esm
Version: 0.8.2
Summary: Lightweight JavaScript ESM module loader for Django.
Keywords: ESM,JavaScript,importmap,Django,module
Author-email: Johannes Maron <johannes@maron.family>
Requires-Python: >=3.10
Classifier: Development Status :: 5 - Production/Stable
Classifier: Programming Language :: Python
Classifier: Environment :: Web Environment
Classifier: Intended Audience :: Developers
Classifier: License :: OSI Approved :: BSD License
Classifier: Operating System :: OS Independent
Classifier: Programming Language :: Python
Classifier: Topic :: Software Development
Classifier: Programming Language :: JavaScript
Classifier: Programming Language :: Python :: 3
Classifier: Programming Language :: Python :: 3 :: Only
Classifier: Programming Language :: Python :: 3.10
Classifier: Programming Language :: Python :: 3.11
Classifier: Programming Language :: Python :: 3.12
Classifier: Programming Language :: Python :: 3.13
Classifier: Programming Language :: Python :: 3.14
Classifier: Framework :: Django
Classifier: Framework :: Django :: 4.2
Classifier: Framework :: Django :: 5.2
Classifier: Framework :: Django :: 6.0
License-File: LICENSE
Requires-Dist: django>=4.2
Requires-Dist: whitenoise>=6.0 ; extra == "whitenoise"
Project-URL: Changelog, https://github.com/codingjoe/django-esm/releases
Project-URL: Documentation, https://github.com/codingjoe/django-esm#django-esm
Project-URL: Issue-Tracker, https://github.com/codingjoe/django-esm/issues
Project-URL: Project-URL, https://github.com/codingjoe/django-esm
Project-URL: Source, https://github.com/codingjoe/django-esm
Provides-Extra: whitenoise
